LICENCE
README.md
setup.py
PyxlSql/__init__.py
PyxlSql/__main__.py
PyxlSql/pyxlAbstracts.py
PyxlSql/pyxlArgs.py
PyxlSql/pyxlEngine.py
PyxlSql/pyxlErrors.py
PyxlSql/pyxlFullHelp.py
PyxlSql/pyxlGrammar.py
PyxlSql/pyxlLicence.py
PyxlSql/pyxlPivot.py
PyxlSql/pyxlResults.py
PyxlSql/pyxlSheets.py
PyxlSql/pyxlSql.py
PyxlSql/pyxlStages.py
PyxlSql/pyxlVersion.py
PyxlSql/pyxlWorkbook.py
excel_sql_engine.egg-info/PKG-INFO
excel_sql_engine.egg-info/SOURCES.txt
excel_sql_engine.egg-info/dependency_links.txt
excel_sql_engine.egg-info/entry_points.txt
excel_sql_engine.egg-info/setup.cfg
excel_sql_engine.egg-info/top_level.txt
tests/test_Northwind.py
tests/test_tooling.py