Metadata-Version: 2.1
Name: excel-sql-engine
Version: 1.6.2
Summary: A tiny SQL engine for Excel files, based on Openpyxl
Home-page: https://gitlab.com/fabien.battini/pyxlsql
Author: Fabien BATTINI
Author-email: fabien.battini@gmail.com
Keywords: excel sql
Classifier: Programming Language :: Python :: 3
Classifier: License :: OSI Approved :: European Union Public Licence 1.2 (EUPL 1.2)
Classifier: Operating System :: OS Independent
Classifier: Development Status :: 5 - Production/Stable
Classifier: Intended Audience :: End Users/Desktop
Classifier: Topic :: Office/Business :: Office Suites
Requires-Python: >=3.6
License-File: LICENCE
